hostport.py
hostport-1.1.dist-info/METADATA
hostport-1.1.dist-info/WHEEL
hostport-1.1.dist-info/top_level.txt
hostport-1.1.dist-info/RECORD
