Metadata-Version: 2.1
Name: hostport
Version: 1.1
Summary: Simple host:port parser
Home-page: https://github.com/zzzsochi/hostport
Author: Zelenyak "ZZZ" Alexander
Author-email: zzz.sochi@gmail.com
License: BSD
Platform: any
Classifier: Development Status :: 5 - Production/Stable
Classifier: Intended Audience :: Developers
Classifier: Operating System :: OS Independent
Classifier: Programming Language :: Python :: 3
